bugout/__init__.py
bugout/__main__.py
bugout/app.py
bugout/calls.py
bugout/data.py
bugout/exceptions.py
bugout/group.py
bugout/humbug.py
bugout/jobs.py
bugout/journal.py
bugout/py.typed
bugout/resource.py
bugout/settings.py
bugout/user.py
bugout-0.2.17.dist-info/LICENSE
bugout-0.2.17.dist-info/METADATA
bugout-0.2.17.dist-info/WHEEL
bugout-0.2.17.dist-info/entry_points.txt
bugout-0.2.17.dist-info/top_level.txt
bugout-0.2.17.dist-info/RECORD
