Metadata-Version: 2.1
Name: bugout
Version: 0.2.17
Summary: Python client library for Bugout API
Home-page: https://github.com/bugout-dev/bugout-python
Author: Bugout
Author-email: engineering@bugout.dev
License: MIT
Platform: all
Classifier: Development Status :: 2 - Pre-Alpha
Classifier: Intended Audience :: Developers
Classifier: Natural Language :: English
Classifier: Programming Language :: Python
Classifier: Programming Language :: Python :: 3
Classifier: Programming Language :: Python :: 3.8
Classifier: Programming Language :: Python :: Implementation :: CPython
Classifier: Topic :: Software Development :: Libraries
Classifier: Topic :: Software Development :: Libraries :: Python Modules
Requires-Python: >=3.6
License-File: LICENSE
Requires-Dist: pydantic<=1.10.10
Requires-Dist: requests
Provides-Extra: dev
Requires-Dist: black; extra == "dev"
Requires-Dist: mypy; extra == "dev"
Requires-Dist: isort; extra == "dev"
Requires-Dist: types-requests; extra == "dev"
Provides-Extra: distribute
Requires-Dist: setuptools; extra == "distribute"
Requires-Dist: twine; extra == "distribute"
Requires-Dist: wheel; extra == "distribute"
